datasette_faiss/__init__.py
datasette_faiss-0.2.1.dist-info/LICENSE
datasette_faiss-0.2.1.dist-info/METADATA
datasette_faiss-0.2.1.dist-info/WHEEL
datasette_faiss-0.2.1.dist-info/entry_points.txt
datasette_faiss-0.2.1.dist-info/top_level.txt
datasette_faiss-0.2.1.dist-info/RECORD
