Metadata-Version: 2.1
Name: datasette-faiss
Version: 0.2.1
Summary: Maintain a FAISS index for specified Datasette tables
Home-page: https://github.com/simonw/datasette-faiss
Author: Simon Willison
License: Apache License, Version 2.0
Project-URL: Issues, https://github.com/simonw/datasette-faiss/issues
Project-URL: CI, https://github.com/simonw/datasette-faiss/actions
Project-URL: Changelog, https://github.com/simonw/datasette-faiss/releases
Classifier: Framework :: Datasette
Classifier: License :: OSI Approved :: Apache Software License
Requires-Python: >=3.7
License-File: LICENSE
Requires-Dist: datasette
Requires-Dist: faiss-cpu
Requires-Dist: numpy <2.0,>=1.0
Provides-Extra: test
Requires-Dist: pytest ; extra == 'test'
Requires-Dist: pytest-asyncio ; extra == 'test'
